structjsonfield/__init__.py
structjsonfield/apps.py
structjsonfield/forms.py
structjsonfield/widgets.py
structjsonfield/static/css/structjsonfield.css
structjsonfield/static/js/structjsonfield.js
structjsonfield/templates/structjsonfield/line_template.html
structjsonfield/templates/structjsonfield/widget.html
structjsonfield-0.1.4.dist-info/DESCRIPTION.rst
structjsonfield-0.1.4.dist-info/METADATA
structjsonfield-0.1.4.dist-info/RECORD
structjsonfield-0.1.4.dist-info/WHEEL
structjsonfield-0.1.4.dist-info/metadata.json
structjsonfield-0.1.4.dist-info/top_level.txt
