Metadata-Version: 2.0
Name: structjsonfield
Version: 0.1.4
Summary: Adding more structure to JSONFields
Home-page: https://github.com/tleguijt/structjsonfield
Author: Tim Leguijt
Author-email: info@leguijtict.nl
License: BSD
Keywords: structjsonfield
Platform: UNKNOWN
Classifier: Development Status :: 3 - Alpha
Classifier: Framework :: Django
Classifier: Framework :: Django :: 1.9
Classifier: Framework :: Django :: 1.10
Classifier: Framework :: Django :: 1.11
Classifier: Intended Audience :: Developers
Classifier: License :: OSI Approved :: BSD License
Classifier: Natural Language :: English
Classifier: Programming Language :: Python :: 3
Classifier: Programming Language :: Python :: 3.5
Classifier: Programming Language :: Python :: 3.6
Classifier: Topic :: Software Development :: Libraries :: Python Modules
